xpcsviewer/__init__.py
xpcsviewer/cli_main.py
xpcsviewer/default_setting.py
xpcsviewer/file_locator.py
xpcsviewer/icons_rc.py
xpcsviewer/viewer_kernel.py
xpcsviewer/viewer_ui.py
xpcsviewer/xpcs_file.py
xpcsviewer/xpcs_viewer.py
xpcsviewer/cli/__init__.py
xpcsviewer/cli/twotime_batch.py
xpcsviewer/configure/aps_8idi.json
xpcsviewer/constants/__init__.py
xpcsviewer/constants/defaults.py
xpcsviewer/constants/fitting.py
xpcsviewer/constants/limits.py
xpcsviewer/constants/thresholds.py
xpcsviewer/constants/timeouts.py
xpcsviewer/fileIO/__init__.py
xpcsviewer/fileIO/aps_8idi.py
xpcsviewer/fileIO/ftype_utils.py
xpcsviewer/fileIO/hdf_reader.py
xpcsviewer/fileIO/hdf_reader_enhanced.py
xpcsviewer/fileIO/qmap_utils.py
xpcsviewer/gui/__init__.py
xpcsviewer/gui/initialization_validator.py
xpcsviewer/gui/shortcuts/__init__.py
xpcsviewer/gui/shortcuts/shortcut_manager.py
xpcsviewer/gui/state/__init__.py
xpcsviewer/gui/state/preferences.py
xpcsviewer/gui/state/recent_paths.py
xpcsviewer/gui/state/session_manager.py
xpcsviewer/gui/theme/__init__.py
xpcsviewer/gui/theme/manager.py
xpcsviewer/gui/theme/plot_themes.py
xpcsviewer/gui/theme/tokens.py
xpcsviewer/gui/theme/styles/base.qss
xpcsviewer/gui/theme/styles/dark.qss
xpcsviewer/gui/theme/styles/light.qss
xpcsviewer/gui/widgets/__init__.py
xpcsviewer/gui/widgets/command_palette.py
xpcsviewer/gui/widgets/drag_drop_list.py
xpcsviewer/gui/widgets/empty_state.py
xpcsviewer/gui/widgets/error_dialog.py
xpcsviewer/gui/widgets/toast_notification.py
xpcsviewer/helper/__init__.py
xpcsviewer/helper/fitting.py
xpcsviewer/helper/listmodel.py
xpcsviewer/helper/logwriter.py
xpcsviewer/helper/utils.py
xpcsviewer/module/__init__.py
xpcsviewer/module/average_toolbox.py
xpcsviewer/module/g2mod.py
xpcsviewer/module/intt.py
xpcsviewer/module/saxs1d.py
xpcsviewer/module/saxs2d.py
xpcsviewer/module/stability.py
xpcsviewer/module/tauq.py
xpcsviewer/module/twotime.py
xpcsviewer/module/twotime_utils.py
xpcsviewer/plothandler/__init__.py
xpcsviewer_gui-0.1.2.dist-info/licenses/AUTHORS.md
xpcsviewer_gui-0.1.2.dist-info/licenses/LICENSE
xpcsviewer_gui-0.1.2.dist-info/METADATA
xpcsviewer_gui-0.1.2.dist-info/WHEEL
xpcsviewer_gui-0.1.2.dist-info/entry_points.txt
xpcsviewer_gui-0.1.2.dist-info/top_level.txt
xpcsviewer_gui-0.1.2.dist-info/RECORD
