Metadata-Version: 2.4
Name: xpcsviewer-gui
Version: 0.1.2
Summary: XPCS Viewer: A python-based interactive tool to visualize and model XPCS dataset
Author-email: Miaoqi Chu <mqichu@anl.gov>, Wei Chen <wchen@anl.gov>
Maintainer-email: Miaoqi Chu <mqichu@anl.gov>, Wei Chen <wchen@anl.gov>
License: MIT License
Project-URL: Homepage, https://github.com/imewei/xpcsviewer
Project-URL: Bug Tracker, https://github.com/imewei/xpcsviewer/issues
Project-URL: Documentation, https://github.com/imewei/xpcsviewer/tree/master/docs
Project-URL: Source Code, https://github.com/imewei/xpcsviewer
Project-URL: Changelog, https://github.com/imewei/xpcsviewer/blob/master/HISTORY.rst
Keywords: XPCS,X-ray,photon correlation spectroscopy,synchrotron,visualization,science
Classifier: Development Status :: 4 - Beta
Classifier: Intended Audience :: Science/Research
Classifier: Intended Audience :: Developers
Classifier: Topic :: Scientific/Engineering
Classifier: Topic :: Scientific/Engineering :: Physics
Classifier: Topic :: Scientific/Engineering :: Visualization
Classifier: Topic :: Software Development :: Libraries :: Python Modules
Classifier: License :: OSI Approved :: MIT License
Classifier: Programming Language :: Python
Classifier: Programming Language :: Python :: 3
Classifier: Programming Language :: Python :: 3.12
Classifier: Programming Language :: Python :: 3.13
Classifier: Operating System :: OS Independent
Classifier: Natural Language :: English
Requires-Python: >=3.12
License-File: LICENSE
License-File: AUTHORS.md
Requires-Dist: pyside6>=6.10.1
Requires-Dist: numpy>=2.3.0
Requires-Dist: scipy>=1.16.0
Requires-Dist: h5py>=3.15.0
Requires-Dist: matplotlib>=3.10.0
Requires-Dist: pyqtgraph>=0.14.0
Requires-Dist: pandas>=2.3.0
Requires-Dist: scikit-learn>=1.8.0
Requires-Dist: scikit-image>=0.25.0
Requires-Dist: joblib>=1.5.0
Requires-Dist: tqdm>=4.67.1
Requires-Dist: psutil>=7.1.0
Requires-Dist: hdf5plugin>=6.0.0
Provides-Extra: dev
Requires-Dist: coverage[toml]>=7.13.0; extra == "dev"
Requires-Dist: pytest>=9.0.0; extra == "dev"
Requires-Dist: pytest-cov>=7.0.0; extra == "dev"
Requires-Dist: pytest-xdist[psutil]>=3.8.0; extra == "dev"
Requires-Dist: pytest-benchmark>=5.2.0; extra == "dev"
Requires-Dist: pytest-mock>=3.15.0; extra == "dev"
Requires-Dist: pytest-timeout>=2.4.0; extra == "dev"
Requires-Dist: pytest-sugar>=1.1.0; extra == "dev"
Requires-Dist: pytest-html>=4.1.1; extra == "dev"
Requires-Dist: pytest-qt>=4.5.0; extra == "dev"
Requires-Dist: hypothesis>=6.148.0; extra == "dev"
Requires-Dist: mypy>=1.19.0; extra == "dev"
Requires-Dist: ruff>=0.14.0; extra == "dev"
Requires-Dist: bandit[toml]>=1.9.0; extra == "dev"
Requires-Dist: pre-commit>=4.5.0; extra == "dev"
Requires-Dist: build>=1.2.0; extra == "dev"
Requires-Dist: twine>=6.0.0; extra == "dev"
Provides-Extra: test
Requires-Dist: pytest>=9.0.0; extra == "test"
Requires-Dist: pytest-qt>=4.5.0; extra == "test"
Requires-Dist: pytest-xdist[psutil]>=3.8.0; extra == "test"
Requires-Dist: pytest-timeout>=2.4.0; extra == "test"
Requires-Dist: pytest-sugar>=1.1.0; extra == "test"
Requires-Dist: pytest-mock>=3.15.0; extra == "test"
Provides-Extra: docs
Requires-Dist: sphinx>=8.2.0; extra == "docs"
Requires-Dist: furo>=2024.8.6; extra == "docs"
Requires-Dist: myst-parser>=4.0.1; extra == "docs"
Requires-Dist: sphinx-autodoc-typehints>=3.5.0; extra == "docs"
Requires-Dist: sphinx-copybutton>=0.5.2; extra == "docs"
Provides-Extra: validation
Requires-Dist: memory-profiler>=0.61.0; extra == "validation"
Requires-Dist: line-profiler>=5.0.0; sys_platform != "win32" and extra == "validation"
Requires-Dist: py-spy>=0.3.0; sys_platform == "linux" and extra == "validation"
Provides-Extra: performance
Requires-Dist: pytest-benchmark>=5.2.0; extra == "performance"
Requires-Dist: memory-profiler>=0.61.0; extra == "performance"
Requires-Dist: pympler>=1.1; extra == "performance"
Provides-Extra: all
Requires-Dist: xpcsviewer-gui[dev,docs,performance,test,validation]; extra == "all"
Dynamic: license-file
